{"id":"223","title":"小雅 · 鱼藻之什 · 角弓","original":["骍骍角弓，翩其反矣。兄弟婚姻，无胥远矣。","尔之远矣，民胥然矣。尔之教矣，民胥效矣。","此令兄弟，绰绰有裕。不令兄弟，交相为愈。","民之无良，相怨一方。受爵不让，至于已斯亡。","老马反为驹，不顾其后。如食宜饇，如酌孔取。","毋教猱升木，如涂涂附。君子有徽猷，小人与属。","雨雪瀌瀌，见晛曰消。莫肯下遗，式居娄骄。","雨雪浮浮，见晛曰流。如蛮如髦，我是用忧。"],"modern":["马儿奔跑，角弓轻快地回转。兄弟之间的婚姻，不应远离亲近。","你远离了，百姓都这样。你的教导，百姓都效法。","这样命令兄弟，宽裕而有余。不命令兄弟，彼此反而更好。","百姓没有善良的人，互相怨恨一方。接受爵位不谦让，最终导致灭亡。","老马变成小马驹，不回头看后面。吃东西要适口，喝酒要适量。","不要教猴子爬树，就像涂抹泥土一样。君子有美好的谋划，小人只会附和。","雨雪纷纷，见到太阳说会消融。没人愿意下来，大家都住在楼阁里骄傲自满。","雨雪飘浮，见到太阳说会流走。像蛮族和毛发，我因此感到忧愁。"],"translationStatus":"complete"}
