{"id":"024","title":"第二十四卦 · ","original":["復","復：亨。出入無疾，朋來無咎。反復其道，七日來復，利有攸往。","彖曰：復亨；剛反，動而以順行，是以出入無疾，朋來無咎。反復其道，七日來復，天行也。利有攸往，剛長也。復其見天地之心乎？","象曰：雷在地中，復；先王以至日閉關，商旅不行，后不省方。","初九：不復遠，無祗悔，元吉。象曰：不遠之復，以修身也。","六二：休復，吉。象曰：休復之吉，以下仁也。","六三：頻復厲，無咎。象曰：頻復之厲，義無咎也。","六四：中行獨復。象曰：中行獨復，以從道也。","六五：敦復，無悔。象曰：敦復無悔，中以自考也。","上六：迷復，凶，有災眚。用行師，終有大敗，以其國君，凶；至于十年，不克征。象曰：迷復之凶，反君道也。"],"modern":["复","复：通达。出入无病痛，朋友来访无灾祸。反复其道，七日后复来，有利于有所往。","彖曰：复通达；刚强反转，行动顺从，所以出入无病痛，朋友来访无灾祸。反复其道，七日后复来，是天道运行。利于有所往，是刚强成长。复，是显现天地之心吗？","象曰：雷在地中，是复；先王在至日闭关，商旅不行，君主不巡视地方。","初九：不远反复，无忧悔，元吉。象曰：不远的反复，是修养自身。","六二：休息反复，吉祥。象曰：休息反复的吉祥，是因为下面仁爱。","六三：频繁反复，危险，但无灾祸。象曰：频繁反复的危险，是义理上的无灾。","六四：中正地独自反复。象曰：中正地独自反复，是因为顺从正道。","六五：敦厚地反复，无悔恨。象曰：敦厚地反复无悔，是内心自我检验。","上六：迷失反复，凶险，有灾祸。用兵，最终大败，因为国君凶险；直到十年，也不能征伐。象曰：迷失反复的凶险，是背离君主之道。"],"translationStatus":"complete"}
