{"id":"034","title":"第三十四卦 · ","original":["大壯","大壯：利貞。","彖曰：大壯，大者壯也。剛以動，故壯。大壯利貞；大者正也。正大而天地之情可見矣！","象曰：雷在天上，大壯；君子以非禮弗履。","初九：壯于趾，征凶，有孚。象曰：壯于趾，其孚窮也。","九二：貞吉。象曰：九二貞吉，以中也。","九三：小人用壯，君子用罔，貞厲。羝羊觸藩，羸其角。象曰：小人用壯，君子罔也。","九四：貞吉悔亡，藩決不羸，壯于大輿之輹。象曰：藩決不羸，尚往也。","六五：喪羊于易，無悔。象曰：喪羊于易，位不當也。","上六：羝羊觸藩，不能退，不能遂，無攸利，艱則吉。象曰：不能退，不能遂，不祥也。艱則吉，咎不長也。"],"modern":["卦名：大壮。","大壮卦爻辞说：有利于坚守正道。","彖传说：大壮，意思是强壮。刚强而行动，所以强壮。大壮有利于坚守正道；大是正的意思。正大，天地的本性就能显现。","象传说：雷在天上，象征大壮；君子因此不做不合礼法的事。","初九爻辞说：脚趾强壮，出征凶险，但有诚信。象传解释说：脚趾强壮，说明诚信到了极点。","九二爻辞说：坚守正道吉祥。象传解释说：九二坚守正道吉祥，是因为处于中正位置。","九三爻辞说：小人用强力，君子用欺骗，坚守正道危险。公羊撞栏杆，角受伤。象传解释说：小人用强力，君子用欺骗。","九四爻辞说：坚守正道吉祥，悔恨消失。栏杆断裂不受伤，强壮如大车的轴辐。象传解释说：栏杆断裂不受伤，说明还可以前进。","六五爻辞说：在易地丢失羊，没有悔恨。象传解释说：丢失羊在易地，是因为位置不合适。","上六爻辞说：公羊撞栏杆，不能后退，也不能前进，没有利益，艰难时反而吉祥。象传解释说：不能后退也不能前进是不吉利的。艰难时吉祥，说明灾难不会长久。"],"translationStatus":"complete"}
