{"id":"363","title":"历代志上 · 1 Chronicles · 第25章","original":["1　וַיַּבְדֵּל דָּוִיד וְשָׂרֵי הַצָּבָא לַעֲבֹדָה לִבְנֵי אָסָף וְהֵימָן וִידוּתוּן הַנְּבִּיאִים בְּכִנֹּרוֹת בִּנְבָלִים וּבִמְצִלְתָּיִם וַיְהִי מִסְפָּרָם אַנְשֵׁי מְלָאכָה לַעֲבֹדָתָם ׃","2　לִבְנֵי אָסָף זַכּוּר וְיוֹסֵף וּנְתַנְיָה וַאֲשַׂרְאֵלָה בְּנֵי אָסָף עַל יַד־אָסָף הַנִּבָּא עַל־יְדֵי הַמֶּלֶךְ ׃","3　לִידוּתוּן בְּנֵי יְדוּתוּן גְּדַלְיָהוּ וּצְרִי וִישַׁעְיָהוּ חֲשַׁבְיָהוּ וּמַתִּתְיָהוּ שִׁשָּׁה עַל יְדֵי אֲבִיהֶם יְדוּתוּן בַּכִּנּוֹר הַנִּבָּא עַל־הֹדוֹת וְהַלֵּל לַיהוָה ׃ ס","4　לְהֵימָן בְּנֵי הֵימָן בֻּקִּיָּהוּ מַתַּנְיָהוּ עֻזִּיאֵל שְׁבוּאֵל וִירִימוֹת חֲנַנְיָה חֲנָנִי אֱלִיאָתָה גִדַּלְתִּי וְרֹמַמְתִּי עֶזֶר יָשְׁבְּקָשָׁה מַלּוֹתִי הוֹתִיר מַחֲזִיאוֹת ׃","5　כָּל־אֵלֶּה בָנִים לְהֵימָן חֹזֵה הַמֶּלֶךְ בְּדִבְרֵי הָאֱלֹהִים לְהָרִים קָרֶן וַיִּתֵּן הָאֱלֹהִים לְהֵימָן בָּנִים אַרְבָּעָה עָשָׂר וּבָנוֹת שָׁלוֹשׁ ׃","6　כָּל־אֵלֶּה עַל־יְדֵי אֲבִיהֶם בַּשִּׁיר בֵּית יְהוָה בִּמְצִלְתַּיִם נְבָלִים וְכִנֹּרוֹת לַעֲבֹדַת בֵּית הָאֱלֹהִים עַל יְדֵי הַמֶּלֶךְ ס אָסָף וִידוּתוּן וְהֵימָן ׃","7　וַיְהִי מִסְפָּרָם עִם־אֲחֵיהֶם מְלֻמְּדֵי־שִׁיר לַיהוָה כָּל־הַמֵּבִין מָאתַיִם שְׁמוֹנִים וּשְׁמוֹנָה ׃","8　וַיַּפִּילוּ גּוֹרָלוֹת מִשְׁמֶרֶת לְעֻמַּת כַּקָּטֹן כַּגָּדוֹל מֵבִין עִם־תַּלְמִיד ׃ פ","9　וַיֵּצֵא הַגּוֹרָל הָרִאשׁוֹן לְאָסָף לְיוֹסֵף גְּדַלְיָהוּ הַשֵּׁנִי הוּא־וְאֶחָיו וּבָנָיו שְׁנֵים עָשָׂר ׃","10　הַשְּׁלִשִׁי זַכּוּר בָּנָיו וְאֶחָיו שְׁנֵים עָשָׂר ׃","11　הָרְבִיעִי לַיִּצְרִי בָּנָיו וְאֶחָיו שְׁנֵים עָשָׂר ׃","12　הַחֲמִישִׁי נְתַנְיָהוּ בָּנָיו וְאֶחָיו שְׁנֵים עָשָׂר ׃","13　הַשִּׁשִּׁי בֻקִּיָּהוּ בָּנָיו וְאֶחָיו שְׁנֵים עָשָׂר ׃","14　הַשְּׁבִעִי יְשַׂרְאֵלָה בָּנָיו וְאֶחָיו שְׁנֵים עָשָׂר ׃","15　הַשְּׁמִינִי יְשַׁעְיָהוּ בָּנָיו וְאֶחָיו שְׁנֵים עָשָׂר ׃","16　הַתְּשִׁיעִי מַתַּנְיָהוּ בָּנָיו וְאֶחָיו שְׁנֵים עָשָׂר ׃","17　הָעֲשִׂירִי שִׁמְעִי בָּנָיו וְאֶחָיו שְׁנֵים עָשָׂר ׃","18　עַשְׁתֵּי־עָשָׂר עֲזַרְאֵל בָּנָיו וְאֶחָיו שְׁנֵים עָשָׂר ׃","19　הַשְּׁנֵים עָשָׂר לַחֲשַׁבְיָה בָּנָיו וְאֶחָיו שְׁנֵים עָשָׂר ׃","20　לִשְׁלֹשָׁה עָשָׂר שׁוּבָאֵל בָּנָיו וְאֶחָיו שְׁנֵים עָשָׂר ׃","21　לְאַרְבָּעָה עָשָׂר מַתִּתְיָהוּ בָּנָיו וְאֶחָיו שְׁנֵים עָשָׂר ׃","22　לַחֲמִשָּׁה עָשָׂר לִירֵמוֹת בָּנָיו וְאֶחָיו שְׁנֵים עָשָׂר ׃","23　לְשִׁשָּׁה עָשָׂר לַחֲנַנְיָהוּ בָּנָיו וְאֶחָיו שְׁנֵים עָשָׂר ׃","24　לְשִׁבְעָה עָשָׂר לְיָשְׁבְּקָשָׁה בָּנָיו וְאֶחָיו שְׁנֵים עָשָׂר ׃","25　לִשְׁמוֹנָה עָשָׂר לַחֲנָנִי בָּנָיו וְאֶחָיו שְׁנֵים עָשָׂר ׃","26　לְתִשְׁעָה עָשָׂר לְמַלּוֹתִי בָּנָיו וְאֶחָיו שְׁנֵים עָשָׂר ׃","27　לְעֶשְׂרִים לֶאֱלִיָּתָה בָּנָיו וְאֶחָיו שְׁנֵים עָשָׂר ׃","28　לְאֶחָד וְעֶשְׂרִים לְהוֹתִיר בָּנָיו וְאֶחָיו שְׁנֵים עָשָׂר ׃","29　לִשְׁנַיִם וְעֶשְׂרִים לְגִדַּלְתִּי בָּנָיו וְאֶחָיו שְׁנֵים עָשָׂר ׃","30　לִשְׁלֹשָׁה וְעֶשְׂרִים לְמַחֲזִיאוֹת בָּנָיו וְאֶחָיו שְׁנֵים עָשָׂר ׃","31　לְאַרְבָּעָה וְעֶשְׂרִים לְרוֹמַמְתִּי עָזֶר בָּנָיו וְאֶחָיו שְׁנֵים עָשָׂר ׃ פ"],"modern":["1　大卫和众首领分派亚萨、希幔，并耶杜顿的子孙弹琴、鼓瑟、敲钹、唱歌。他们供职的人数记在下面：","2　亚萨的儿子撒刻、约瑟、尼探雅、亚萨利拉都归亚萨指教，遵王的旨意唱歌。","3　耶杜顿的儿子基大利、西利、耶筛亚、哈沙比雅、玛他提雅、示每共六人，都归他们父亲耶杜顿指教，弹琴，唱歌，称谢，颂赞耶和华。","4　希幔的儿子布基雅、玛探雅、乌薛、细布业、耶利摩、哈拿尼雅、哈拿尼、以利亚他、基大利提、罗幔提·以谢、约施比加沙、玛罗提、何提、玛哈秀；","5　这都是希幔的儿子，吹角颂赞。希幔奉　神之命作王的先见。　神赐给希幔十四个儿子，三个女儿，","6　都归他们父亲指教，在耶和华的殿唱歌、敲钹、弹琴、鼓瑟，办　神殿的事务。亚萨、耶杜顿、希幔都是王所命定的。","7　他们和他们的弟兄学习颂赞耶和华；善于歌唱的共有二百八十八人。","8　这些人无论大小，为师的、为徒的，都一同掣签分了班次。","9　掣签的时候，第一掣出来的是亚萨的儿子约瑟。第二是基大利；他和他弟兄并儿子共十二人。","10　第三是撒刻；他和他儿子并弟兄共十二人。","11　第四是伊洗利；他和他儿子并弟兄共十二人。","12　第五是尼探雅；他和他儿子并弟兄共十二人。","13　第六是布基雅；他和他儿子并弟兄共十二人。","14　第七是耶萨利拉；他和他儿子并弟兄共十二人。","15　第八是耶筛亚；他和他儿子并弟兄共十二人。","16　第九是玛探雅；他和他儿子并弟兄共十二人。","17　第十是示每；他和他儿子并弟兄共十二人。","18　第十一是亚萨烈；他和他儿子并弟兄共十二人。","19　第十二是哈沙比雅；他和他儿子并弟兄共十二人。","20　第十三是书巴业；他和他儿子并弟兄共十二人。","21　第十四是玛他提雅；他和他儿子并弟兄共十二人。","22　第十五是耶利摩；他和他儿子并弟兄共十二人。","23　第十六是哈拿尼雅；他和他儿子并弟兄共十二人。","24　第十七是约施比加沙；他和他儿子并弟兄共十二人。","25　第十八是哈拿尼；他和他儿子并弟兄共十二人。","26　第十九是玛罗提；他和他儿子并弟兄共十二人。","27　第二十是以利亚他；他和他儿子并弟兄共十二人。","28　第二十一是何提；他和他儿子并弟兄共十二人。","29　第二十二是基大利提；他和他儿子并弟兄共十二人。","30　第二十三是玛哈秀；他和他儿子并弟兄共十二人。","31　第二十四是罗幔提·以谢；他和他儿子并弟兄共十二人。"],"translationStatus":"complete"}
