{"id":"772","title":"耶利米书 · 第27章","original":["1　猶大王約西亞的兒子約雅敬登基的時候，有這話從耶和華臨到耶利米說：","2　「耶和華對我如此說：你做繩索與軛，加在自己的頸項上，","3　藉那些來到耶路撒冷見猶大王西底家的使臣之手，把繩索與軛送到以東王、摩押王、亞捫王、泰爾王、西頓王那裏，","4　且囑咐使臣，傳與他們的主人說，萬軍之耶和華－以色列的上帝如此說：","5　我用大能和伸出來的膀臂，創造大地和地上的人民、牲畜。我看給誰相宜，就把地給誰。","6　現在我將這些地都交給我僕人巴比倫王尼布甲尼撒的手，我也將田野的走獸給他使用。","7　列國都必服事他和他的兒孫，直到他本國[遭報]的日期來到。那時，多國和大君王要使他作他們的奴僕。","8　「無論哪一邦哪一國，不肯服事這巴比倫王尼布甲尼撒，也不把頸項放在巴比倫王的軛下，我必用刀劍、饑荒、瘟疫刑罰那邦，直到我藉巴比倫王的手將他們毀滅。這是耶和華說的。","9　至於你們，不可聽從你們的先知和占卜的、圓夢的、觀兆的，以及行邪術的；他們告訴你們說：『你們不致服事巴比倫王。』","10　他們向你們說假預言，要叫你們遷移，遠離本地，以致我將你們趕出去，使你們滅亡。","11　但哪一邦肯把頸項放在巴比倫王的軛下服事他，我必使那邦仍在本地存留，得以耕種居住。這是耶和華說的。」","12　我就照這一切的話對猶大王西底家說：「要把你們的頸項放在巴比倫王的軛下，服事他和他的百姓，便得存活。","13　你和你的百姓為何要因刀劍、饑荒、瘟疫死亡，正如耶和華論到不服事巴比倫王的那國說的話呢？","14　不可聽那些先知對你們所說的話；他們說：『你們不致服事巴比倫王』，其實他們向你們說假預言。","15　耶和華說：『我並沒有打發他們，他們卻託我的名說假預言，好使我將你們和向你們說預言的那些先知趕出去，一同滅亡。』」","16　我又對祭司和這眾民說：「耶和華如此說：你們不可聽那先知對你們所說的預言。他們說：『耶和華殿中的器皿快要從巴比倫帶回來』；其實他們向你們說假預言。","17　不可聽從他們，只管服事巴比倫王便得存活。這城何致變為荒場呢？","18　他們若果是先知，有耶和華的話臨到他們，讓他們祈求萬軍之耶和華，使那在耶和華殿中和猶大王宮內，並耶路撒冷剩下的器皿，不被帶到巴比倫去。（","19　因為萬軍之耶和華論到柱子、[銅]海、[盆]座，並剩在這城裏的器皿，","20　就是巴比倫王尼布甲尼撒擄掠猶大王約雅敬的兒子耶哥尼雅，和猶大、耶路撒冷一切貴冑的時候所沒有掠去的器皿。）","21　論到那在耶和華殿中和猶大王宮內，並耶路撒冷剩下的器皿，萬軍之耶和華－以色列的上帝如此說：","22　必被帶到巴比倫存在那裏，直到我眷顧以色列人的日子。那時，我必將這器皿帶回來，交還此地。這是耶和華說的。」"],"modern":["1　犹大王约西亚的儿子约雅敬登基的时候，有这话从耶和华临到耶利米说：","2　「耶和华对我如此说：你做绳索与轭，加在自己的颈项上，","3　借那些来到耶路撒冷见犹大王西底家的使臣之手，把绳索与轭送到以东王、摩押王、亚扪王、泰尔王、西顿王那里，","4　且嘱咐使臣，传与他们的主人说，万军之耶和华—以色列的　神如此说：","5　我用大能和伸出来的膀臂，创造大地和地上的人民、牲畜。我看给谁相宜，就把地给谁。","6　现在我将这些地都交给我仆人巴比伦王尼布甲尼撒的手，我也将田野的走兽给他使用。","7　列国都必服事他和他的儿孙，直到他本国[遭报]的日期来到。那时，多国和大君王要使他作他们的奴仆。","8　「无论哪一邦哪一国，不肯服事这巴比伦王尼布甲尼撒，也不把颈项放在巴比伦王的轭下，我必用刀剑、饥荒、瘟疫刑罚那邦，直到我借巴比伦王的手将他们毁灭。这是耶和华说的。","9　至于你们，不可听从你们的先知和占卜的、圆梦的、观兆的，以及行邪术的；他们告诉你们说：『你们不致服事巴比伦王。』","10　他们向你们说假预言，要叫你们迁移，远离本地，以致我将你们赶出去，使你们灭亡。","11　但哪一邦肯把颈项放在巴比伦王的轭下服事他，我必使那邦仍在本地存留，得以耕种居住。这是耶和华说的。」","12　我就照这一切的话对犹大王西底家说：「要把你们的颈项放在巴比伦王的轭下，服事他和他的百姓，便得存活。","13　你和你的百姓为何要因刀剑、饥荒、瘟疫死亡，正如耶和华论到不服事巴比伦王的那国说的话呢？","14　不可听那些先知对你们所说的话；他们说：『你们不致服事巴比伦王』，其实他们向你们说假预言。","15　耶和华说：『我并没有打发他们，他们却托我的名说假预言，好使我将你们和向你们说预言的那些先知赶出去，一同灭亡。』」","16　我又对祭司和这众民说：「耶和华如此说：你们不可听那先知对你们所说的预言。他们说：『耶和华殿中的器皿快要从巴比伦带回来』；其实他们向你们说假预言。","17　不可听从他们，只管服事巴比伦王便得存活。这城何致变为荒场呢？","18　他们若果是先知，有耶和华的话临到他们，让他们祈求万军之耶和华，使那在耶和华殿中和犹大王宫内，并耶路撒冷剩下的器皿，不被带到巴比伦去。（","19　因为万军之耶和华论到柱子、[铜]海、[盆]座，并剩在这城里的器皿，","20　就是巴比伦王尼布甲尼撒掳掠犹大王约雅敬的儿子耶哥尼雅，和犹大、耶路撒冷一切贵胄的时候所没有掠去的器皿。）","21　论到那在耶和华殿中和犹大王宫内，并耶路撒冷剩下的器皿，万军之耶和华—以色列的　神如此说：","22　必被带到巴比伦存在那里，直到我眷顾以色列人的日子。那时，我必将这器皿带回来，交还此地。这是耶和华说的。」"],"translationStatus":"complete"}
