{"id":"775","title":"耶利米书 · 第30章","original":["1　耶和華的話臨到耶利米說：","2　「耶和華－以色列的上帝如此說：你將我對你說過的一切話都寫在書上。","3　耶和華說：日子將到，我要使我的百姓以色列和猶大被擄的人歸回；我也要使他們回到我所賜給他們列祖之地，他們就得這地為業。這是耶和華說的。」","4　以下是耶和華論到以色列和猶大所說的話：","5　耶和華如此說：我們聽見聲音， 是戰抖懼怕而不平安的聲音。","6　你們且訪問看看， 男人有產難嗎？ 我怎麼看見人人用手掐腰， 像產難的婦人， 臉面都變青了呢？","7　哀哉！那日為大， 無日可比； 這是雅各遭難的時候， 但他必被救出來。","8　萬軍之耶和華說：「到那日，我必從你頸項上折斷仇敵的軛，扭開他的繩索；外邦人不得再使你作他們的奴僕。","9　你們卻要事奉耶和華－你們的上帝和我為你們所要興起的王大衛。」","10　故此，耶和華說： 我的僕人雅各啊，不要懼怕； 以色列啊，不要驚惶； 因我要從遠方拯救你， 從被擄到之地拯救你的後裔； 雅各必回來得享平靖安逸， 無人使他害怕。","11　因我與你同在，要拯救你， 也要將所趕散你到的那些國滅絕淨盡， 卻不將你滅絕淨盡，倒要從寬懲治你， 萬不能不罰你。 這是耶和華說的。","12　耶和華如此說： 你的損傷無法醫治； 你的傷痕極其重大。","13　無人為你分訴， 使你的傷痕得以纏裹； 你沒有醫治的良藥。","14　你所親愛的都忘記你， 不來探問你。 我因你的罪孽甚大，罪惡眾多， 曾用仇敵加的傷害傷害你， 用殘忍者的懲治懲治你。","15　你為何因損傷哀號呢？ 你的痛苦無法醫治。 我因你的罪孽甚大，罪惡眾多， 曾將這些加在你身上。","16　故此，凡吞吃你的必被吞吃； 你的敵人個個都被擄去； 擄掠你的必成為擄物； 搶奪你的必成為掠物。","17　耶和華說：我必使你痊癒， 醫好你的傷痕， 都因人稱你為被趕散的， [說]：這是錫安，無人來探問的！","18　耶和華如此說： 我必使雅各被擄去的帳棚歸回， 也必顧惜他的住處。 城必建造在原舊的山岡； 宮殿也照舊有人居住。","19　必有感謝和歡樂的聲音從其中發出， 我要使他們增多，不致減少； 使他們尊榮，不致卑微。","20　他們的兒女要如往日； 他們的會眾堅立在我面前； 凡欺壓他們的，我必刑罰他。","21　他們的君王必是屬乎他們的； 掌權的必從他們中間而出。 我要使他就近我， 他也要親近我； 不然，誰有膽量親近我呢？ 這是耶和華說的。","22　你們要作我的子民， 我要作你們的上帝。","23　看哪，耶和華的忿怒 好像暴風已經發出； 是掃滅的暴風， 必轉到惡人的頭上。","24　耶和華的烈怒必不轉消， 直到他心中所擬定的成就了； 末後的日子你們要明白。"],"modern":["1　耶和华的话临到耶利米说：","2　「耶和华—以色列的　神如此说：你将我对你说过的一切话都写在书上。","3　耶和华说：日子将到，我要使我的百姓以色列和犹大被掳的人归回；我也要使他们回到我所赐给他们列祖之地，他们就得这地为业。这是耶和华说的。」","4　以下是耶和华论到以色列和犹大所说的话：","5　耶和华如此说：我们听见声音， 是战抖惧怕而不平安的声音。","6　你们且访问看看， 男人有产难吗？ 我怎么看见人人用手掐腰， 像产难的妇人， 脸面都变青了呢？","7　哀哉！那日为大， 无日可比； 这是雅各遭难的时候， 但他必被救出来。","8　万军之耶和华说：「到那日，我必从你颈项上折断仇敌的轭，扭开他的绳索；外邦人不得再使你作他们的奴仆。","9　你们却要事奉耶和华—你们的　神和我为你们所要兴起的王大卫。」","10　故此，耶和华说： 我的仆人雅各啊，不要惧怕； 以色列啊，不要惊惶； 因我要从远方拯救你， 从被掳到之地拯救你的后裔； 雅各必回来得享平靖安逸， 无人使他害怕。","11　因我与你同在，要拯救你， 也要将所赶散你到的那些国灭绝净尽， 却不将你灭绝净尽，倒要从宽惩治你， 万不能不罚你。 这是耶和华说的。","12　耶和华如此说： 你的损伤无法医治； 你的伤痕极其重大。","13　无人为你分诉， 使你的伤痕得以缠裹； 你没有医治的良药。","14　你所亲爱的都忘记你， 不来探问你。 我因你的罪孽甚大，罪恶众多， 曾用仇敌加的伤害伤害你， 用残忍者的惩治惩治你。","15　你为何因损伤哀号呢？ 你的痛苦无法医治。 我因你的罪孽甚大，罪恶众多， 曾将这些加在你身上。","16　故此，凡吞吃你的必被吞吃； 你的敌人个个都被掳去； 掳掠你的必成为掳物； 抢夺你的必成为掠物。","17　耶和华说：我必使你痊愈， 医好你的伤痕， 都因人称你为被赶散的， [说]：这是锡安，无人来探问的！","18　耶和华如此说： 我必使雅各被掳去的帐棚归回， 也必顾惜他的住处。 城必建造在原旧的山冈； 宫殿也照旧有人居住。","19　必有感谢和欢乐的声音从其中发出， 我要使他们增多，不致减少； 使他们尊荣，不致卑微。","20　他们的儿女要如往日； 他们的会众坚立在我面前； 凡欺压他们的，我必刑罚他。","21　他们的君王必是属乎他们的； 掌权的必从他们中间而出。 我要使他就近我， 他也要亲近我； 不然，谁有胆量亲近我呢？ 这是耶和华说的。","22　你们要作我的子民， 我要作你们的　神。","23　看哪，耶和华的忿怒 好像暴风已经发出； 是扫灭的暴风， 必转到恶人的头上。","24　耶和华的烈怒必不转消， 直到他心中所拟定的成就了； 末后的日子你们要明白。"],"translationStatus":"complete"}
